<?xml version="1.0" encoding="UTF-8"?>
<service xmlns="http://zstack.org/schema/zstack">
    <id>scheduler</id>
    <interceptor>SchedulerApiInterceptor</interceptor>
    <message>
      <name>org.zstack.scheduler.APIDeleteSchedulerJobMsg</name>
    </message>

    <message>
        <name>org.zstack.scheduler.APIQuerySchedulerJobMsg</name>
        <serviceId>query</serviceId>
    </message>

    <message>
        <name>org.zstack.scheduler.APIUpdateSchedulerJobMsg</name>
    </message>

    <message>
        <name>org.zstack.scheduler.APIChangeSchedulerStateMsg</name>
    </message>

    <message>
        <name>org.zstack.scheduler.APICreateSchedulerTriggerMsg</name>
    </message>

    <message>
        <name>org.zstack.scheduler.APIUpdateSchedulerTriggerMsg</name>
    </message>

    <message>
        <name>org.zstack.scheduler.APIDeleteSchedulerTriggerMsg</name>
    </message>

    <message>
        <name>org.zstack.scheduler.APIAddSchedulerJobToSchedulerTriggerMsg</name>
    </message>

    <message>
        <name>org.zstack.scheduler.APIRemoveSchedulerJobFromSchedulerTriggerMsg</name>
    </message>

    <message>
        <name>org.zstack.scheduler.APICreateSchedulerJobMsg</name>
    </message>

    <message>
        <name>org.zstack.scheduler.APIQuerySchedulerTriggerMsg</name>
        <serviceId>query</serviceId>
    </message>
</service>
